acs_axiom-0.2.0.data/scripts/axiom
axiom/__init__.py
axiom/ccam_test.sh
axiom/config.py
axiom/converters.py
axiom/decorators.py
axiom/drs.old.py
axiom/exceptions.py
axiom/report.py
axiom/supervisor.py
axiom/utilities.py
axiom/automation/__init__.py
axiom/data/domains.json
axiom/data/drs.json
axiom/data/models.json
axiom/data/projects.json
axiom/data/schemas/cf-77.json
axiom/data/schemas/cordex-cmip6.json
axiom/data/schemas/cordex-day.json
axiom/data/schemas/cordex-fx.json
axiom/data/schemas/cordex-month.json
axiom/data/schemas/cordex.json
axiom/data/schemas/mrd-0.1.0.json
axiom/drs/__init__.py
axiom/drs/cli.py
axiom/drs/domain.py
axiom/drs/payload.py
axiom/drs/utilities.py
axiom/drs/processing/__init__.py
axiom/drs/processing/ccam.py
axiom/qa/__init__.py
axiom/qa/cli.py
axiom/schemas/__init__.py
axiom/tests/test_config.py
axiom/tests/test_decorators.py
axiom/tests/test_drs.py
axiom/tests/test_drs_utilities.py
axiom/tests/test_payloads.py
axiom/tests/test_supervisor.py
axiom/tests/test_utilities.py
axiom/tests/data/mrd.xml
axiom/validation/__init__.py
axiom/validation/validator.py
acs_axiom-0.2.0.dist-info/LICENSE
acs_axiom-0.2.0.dist-info/METADATA
acs_axiom-0.2.0.dist-info/WHEEL
acs_axiom-0.2.0.dist-info/top_level.txt
acs_axiom-0.2.0.dist-info/RECORD
